[
 {
  "trends": [
   {
    "name": "#الخميس_الونيس",
    "url": "http://twitter.com/search?q=%23%D8%A7%D9%84%D8%AE%D9%85%D9%8A%D8%B3_%D8%A7%D9%84%D9%88%D9%86%D9%8A%D8%B3",
    "promoted_content": null,
    "query": "%23%D8%A7%D9%84%D8%AE%D9%85%D9%8A%D8%B3_%D8%A7%D9%84%D9%88%D9%86%D9%8A%D8%B3",
    "tweet_volume": 84148
   },
   {
    "name": "#برنامج_نجوم5",
    "url": "http://twitter.com/search?q=%23%D8%A8%D8%B1%D9%86%D8%A7%D9%85%D8%AC_%D9%86%D8%AC%D9%88%D9%855",
    "promoted_content": null,
    "query": "%23%D8%A8%D8%B1%D9%86%D8%A7%D9%85%D8%AC_%D9%86%D8%AC%D9%88%D9%855",
    "tweet_volume": null
   },
   {
    "name": "#دعواتكم_لزهور_سعود",
    "url": "http://twitter.com/search?q=%23%D8%AF%D8%B9%D9%88%D8%A7%D8%AA%D9%83%D9%85_%D9%84%D8%B2%D9%87%D9%88%D8%B1_%D8%B3%D8%B9%D9%88%D8%AF",
    "promoted_content": null,
    "query": "%23%D8%AF%D8%B9%D9%88%D8%A7%D8%AA%D9%83%D9%85_%D9%84%D8%B2%D9%87%D9%88%D8%B1_%D8%B3%D8%B9%D9%88%D8%AF",
    "tweet_volume": null
   },
   {
    "name": "#بدايه_٢_مليون",
    "url": "http://twitter.com/search?q=%23%D8%A8%D8%AF%D8%A7%D9%8A%D9%87_%D9%A2_%D9%85%D9%84%D9%8A%D9%88%D9%86",
    "promoted_content": null,
    "query": "%23%D8%A8%D8%AF%D8%A7%D9%8A%D9%87_%D9%A2_%D9%85%D9%84%D9%8A%D9%88%D9%86",
    "tweet_volume": null
   },
   {
    "name": "#ليله_الجمعه",
    "url": "http://twitter.com/search?q=%23%D9%84%D9%8A%D9%84%D9%87_%D8%A7%D9%84%D8%AC%D9%85%D8%B9%D9%87",
    "promoted_content": null,
    "query": "%23%D9%84%D9%8A%D9%84%D9%87_%D8%A7%D9%84%D8%AC%D9%85%D8%B9%D9%87",
    "tweet_volume": 22839
   },
   {
    "name": "محمد نور",
    "url": "http://twitter.com/search?q=%22%D9%85%D8%AD%D9%85%D8%AF+%D9%86%D9%88%D8%B1%22",
    "promoted_content": null,
    "query": "%22%D9%85%D8%AD%D9%85%D8%AF+%D9%86%D9%88%D8%B1%22",
    "tweet_volume": null
   },
   {
    "name": "يوسف الثنيان",
    "url": "http://twitter.com/search?q=%22%D9%8A%D9%88%D8%B3%D9%81+%D8%A7%D9%84%D8%AB%D9%86%D9%8A%D8%A7%D9%86%22",
    "promoted_content": null,
    "query": "%22%D9%8A%D9%88%D8%B3%D9%81+%D8%A7%D9%84%D8%AB%D9%86%D9%8A%D8%A7%D9%86%22",
    "tweet_volume": null
   },
   {
    "name": "درب الهلاك",
    "url": "http://twitter.com/search?q=%22%D8%AF%D8%B1%D8%A8+%D8%A7%D9%84%D9%87%D9%84%D8%A7%D9%83%22",
    "promoted_content": null,
    "query": "%22%D8%AF%D8%B1%D8%A8+%D8%A7%D9%84%D9%87%D9%84%D8%A7%D9%83%22",
    "tweet_volume": null
   },
   {
    "name": "كريس",
    "url": "http://twitter.com/search?q=%D9%83%D8%B1%D9%8A%D8%B3",
    "promoted_content": null,
    "query": "%D9%83%D8%B1%D9%8A%D8%B3",
    "tweet_volume": null
   },
   {
    "name": "تاريخ اليوم",
    "url": "http://twitter.com/search?q=%22%D8%AA%D8%A7%D8%B1%D9%8A%D8%AE+%D8%A7%D9%84%D9%8A%D9%88%D9%85%22",
    "promoted_content": null,
    "query": "%22%D8%AA%D8%A7%D8%B1%D9%8A%D8%AE+%D8%A7%D9%84%D9%8A%D9%88%D9%85%22",
    "tweet_volume": null
   },
   {
    "name": "اليوم الخميس",
    "url": "http://twitter.com/search?q=%22%D8%A7%D9%84%D9%8A%D9%88%D9%85+%D8%A7%D9%84%D8%AE%D9%85%D9%8A%D8%B3%22",
    "promoted_content": null,
    "query": "%22%D8%A7%D9%84%D9%8A%D9%88%D9%85+%D8%A7%D9%84%D8%AE%D9%85%D9%8A%D8%B3%22",
    "tweet_volume": 18168
   },
   {
    "name": "ياسر القحطاني",
    "url": "http://twitter.com/search?q=%22%D9%8A%D8%A7%D8%B3%D8%B1+%D8%A7%D9%84%D9%82%D8%AD%D8%B7%D8%A7%D9%86%D9%8A%22",
    "promoted_content": null,
    "query": "%22%D9%8A%D8%A7%D8%B3%D8%B1+%D8%A7%D9%84%D9%82%D8%AD%D8%B7%D8%A7%D9%86%D9%8A%22",
    "tweet_volume": null
   },
   {
    "name": "سولو ليسا",
    "url": "http://twitter.com/search?q=%22%D8%B3%D9%88%D9%84%D9%88+%D9%84%D9%8A%D8%B3%D8%A7%22",
    "promoted_content": null,
    "query": "%22%D8%B3%D9%88%D9%84%D9%88+%D9%84%D9%8A%D8%B3%D8%A7%22",
    "tweet_volume": null
   },
   {
    "name": "اليوم الوطني",
    "url": "http://twitter.com/search?q=%22%D8%A7%D9%84%D9%8A%D9%88%D9%85+%D8%A7%D9%84%D9%88%D8%B7%D9%86%D9%8A%22",
    "promoted_content": null,
    "query": "%22%D8%A7%D9%84%D9%8A%D9%88%D9%85+%D8%A7%D9%84%D9%88%D8%B7%D9%86%D9%8A%22",
    "tweet_volume": 32089
   },
   {
    "name": "وسط المطر",
    "url": "http://twitter.com/search?q=%22%D9%88%D8%B3%D8%B7+%D8%A7%D9%84%D9%85%D8%B7%D8%B1%22",
    "promoted_content": null,
    "query": "%22%D9%88%D8%B3%D8%B7+%D8%A7%D9%84%D9%85%D8%B7%D8%B1%22",
    "tweet_volume": null
   },
   {
    "name": "إسماعيل",
    "url": "http://twitter.com/search?q=%D8%A5%D8%B3%D9%85%D8%A7%D8%B9%D9%8A%D9%84",
    "promoted_content": null,
    "query": "%D8%A5%D8%B3%D9%85%D8%A7%D8%B9%D9%8A%D9%84",
    "tweet_volume": null
   },
   {
    "name": "بيكهيون",
    "url": "http://twitter.com/search?q=%D8%A8%D9%8A%D9%83%D9%87%D9%8A%D9%88%D9%86",
    "promoted_content": null,
    "query": "%D8%A8%D9%8A%D9%83%D9%87%D9%8A%D9%88%D9%86",
    "tweet_volume": null
   },
   {
    "name": "اوف الخميس",
    "url": "http://twitter.com/search?q=%22%D8%A7%D9%88%D9%81+%D8%A7%D9%84%D8%AE%D9%85%D9%8A%D8%B3%22",
    "promoted_content": null,
    "query": "%22%D8%A7%D9%88%D9%81+%D8%A7%D9%84%D8%AE%D9%85%D9%8A%D8%B3%22",
    "tweet_volume": null
   },
   {
    "name": "الامارات",
    "url": "http://twitter.com/search?q=%D8%A7%D9%84%D8%A7%D9%85%D8%A7%D8%B1%D8%A7%D8%AA",
    "promoted_content": null,
    "query": "%D8%A7%D9%84%D8%A7%D9%85%D8%A7%D8%B1%D8%A7%D8%AA",
    "tweet_volume": 95897
   },
   {
    "name": "نواف التمياط",
    "url": "http://twitter.com/search?q=%22%D9%86%D9%88%D8%A7%D9%81+%D8%A7%D9%84%D8%AA%D9%85%D9%8A%D8%A7%D8%B7%22",
    "promoted_content": null,
    "query": "%22%D9%86%D9%88%D8%A7%D9%81+%D8%A7%D9%84%D8%AA%D9%85%D9%8A%D8%A7%D8%B7%22",
    "tweet_volume": null
   },
   {
    "name": "فات الفوت",
    "url": "http://twitter.com/search?q=%22%D9%81%D8%A7%D8%AA+%D8%A7%D9%84%D9%81%D9%88%D8%AA%22",
    "promoted_content": null,
    "query": "%22%D9%81%D8%A7%D8%AA+%D8%A7%D9%84%D9%81%D9%88%D8%AA%22",
    "tweet_volume": null
   },
   {
    "name": "DRUMMER JUNGKOOK",
    "url": "http://twitter.com/search?q=%22DRUMMER+JUNGKOOK%22",
    "promoted_content": null,
    "query": "%22DRUMMER+JUNGKOOK%22",
    "tweet_volume": 62665
   },
   {
    "name": "فريق الرويه",
    "url": "http://twitter.com/search?q=%22%D9%81%D8%B1%D9%8A%D9%82+%D8%A7%D9%84%D8%B1%D9%88%D9%8A%D9%87%22",
    "promoted_content": null,
    "query": "%22%D9%81%D8%B1%D9%8A%D9%82+%D8%A7%D9%84%D8%B1%D9%88%D9%8A%D9%87%22",
    "tweet_volume": null
   },
   {
    "name": "فارس عوض",
    "url": "http://twitter.com/search?q=%22%D9%81%D8%A7%D8%B1%D8%B3+%D8%B9%D9%88%D8%B6%22",
    "promoted_content": null,
    "query": "%22%D9%81%D8%A7%D8%B1%D8%B3+%D8%B9%D9%88%D8%B6%22",
    "tweet_volume": null
   },
   {
    "name": "الامور المتروكه",
    "url": "http://twitter.com/search?q=%22%D8%A7%D9%84%D8%A7%D9%85%D9%88%D8%B1+%D8%A7%D9%84%D9%85%D8%AA%D8%B1%D9%88%D9%83%D9%87%22",
    "promoted_content": null,
    "query": "%22%D8%A7%D9%84%D8%A7%D9%85%D9%88%D8%B1+%D8%A7%D9%84%D9%85%D8%AA%D8%B1%D9%88%D9%83%D9%87%22",
    "tweet_volume": null
   },
   {
    "name": "ماجد عبدالله",
    "url": "http://twitter.com/search?q=%22%D9%85%D8%A7%D8%AC%D8%AF+%D8%B9%D8%A8%D8%AF%D8%A7%D9%84%D9%84%D9%87%22",
    "promoted_content": null,
    "query": "%22%D9%85%D8%A7%D8%AC%D8%AF+%D8%B9%D8%A8%D8%AF%D8%A7%D9%84%D9%84%D9%87%22",
    "tweet_volume": null
   },
   {
    "name": "محو الاميه",
    "url": "http://twitter.com/search?q=%22%D9%85%D8%AD%D9%88+%D8%A7%D9%84%D8%A7%D9%85%D9%8A%D9%87%22",
    "promoted_content": null,
    "query": "%22%D9%85%D8%AD%D9%88+%D8%A7%D9%84%D8%A7%D9%85%D9%8A%D9%87%22",
    "tweet_volume": null
   },
   {
    "name": "نصف صديق",
    "url": "http://twitter.com/search?q=%22%D9%86%D8%B5%D9%81+%D8%B5%D8%AF%D9%8A%D9%82%22",
    "promoted_content": null,
    "query": "%22%D9%86%D8%B5%D9%81+%D8%B5%D8%AF%D9%8A%D9%82%22",
    "tweet_volume": null
   },
   {
    "name": "ليت البدايات",
    "url": "http://twitter.com/search?q=%22%D9%84%D9%8A%D8%AA+%D8%A7%D9%84%D8%A8%D8%AF%D8%A7%D9%8A%D8%A7%D8%AA%22",
    "promoted_content": null,
    "query": "%22%D9%84%D9%8A%D8%AA+%D8%A7%D9%84%D8%A8%D8%AF%D8%A7%D9%8A%D8%A7%D8%AA%22",
    "tweet_volume": null
   },
   {
    "name": "ابو ظبي",
    "url": "http://twitter.com/search?q=%22%D8%A7%D8%A8%D9%88+%D8%B8%D8%A8%D9%8A%22",
    "promoted_content": null,
    "query": "%22%D8%A7%D8%A8%D9%88+%D8%B8%D8%A8%D9%8A%22",
    "tweet_volume": null
   },
   {
    "name": "jennie kim",
    "url": "http://twitter.com/search?q=%22jennie+kim%22",
    "promoted_content": null,
    "query": "%22jennie+kim%22",
    "tweet_volume": 203629
   },
   {
    "name": "RM BEST LEADER",
    "url": "http://twitter.com/search?q=%22RM+BEST+LEADER%22",
    "promoted_content": null,
    "query": "%22RM+BEST+LEADER%22",
    "tweet_volume": null
   },
   {
    "name": "THUNDEROUS SO SSIX",
    "url": "http://twitter.com/search?q=%22THUNDEROUS+SO+SSIX%22",
    "promoted_content": null,
    "query": "%22THUNDEROUS+SO+SSIX%22",
    "tweet_volume": 103614
   },
   {
    "name": "حسين عبدالغني",
    "url": "http://twitter.com/search?q=%22%D8%AD%D8%B3%D9%8A%D9%86+%D8%B9%D8%A8%D8%AF%D8%A7%D9%84%D8%BA%D9%86%D9%8A%22",
    "promoted_content": null,
    "query": "%22%D8%AD%D8%B3%D9%8A%D9%86+%D8%B9%D8%A8%D8%AF%D8%A7%D9%84%D8%BA%D9%86%D9%8A%22",
    "tweet_volume": null
   },
   {
    "name": "كيم سابو",
    "url": "http://twitter.com/search?q=%22%D9%83%D9%8A%D9%85+%D8%B3%D8%A7%D8%A8%D9%88%22",
    "promoted_content": null,
    "query": "%22%D9%83%D9%8A%D9%85+%D8%B3%D8%A7%D8%A8%D9%88%22",
    "tweet_volume": null
   },
   {
    "name": "I Vote",
    "url": "http://twitter.com/search?q=%22I+Vote%22",
    "promoted_content": null,
    "query": "%22I+Vote%22",
    "tweet_volume": 574349
   },
   {
    "name": "رييس نادي",
    "url": "http://twitter.com/search?q=%22%D8%B1%D9%8A%D9%8A%D8%B3+%D9%86%D8%A7%D8%AF%D9%8A%22",
    "promoted_content": null,
    "query": "%22%D8%B1%D9%8A%D9%8A%D8%B3+%D9%86%D8%A7%D8%AF%D9%8A%22",
    "tweet_volume": null
   },
   {
    "name": "تعزيز المهارات",
    "url": "http://twitter.com/search?q=%22%D8%AA%D8%B9%D8%B2%D9%8A%D8%B2+%D8%A7%D9%84%D9%85%D9%87%D8%A7%D8%B1%D8%A7%D8%AA%22",
    "promoted_content": null,
    "query": "%22%D8%AA%D8%B9%D8%B2%D9%8A%D8%B2+%D8%A7%D9%84%D9%85%D9%87%D8%A7%D8%B1%D8%A7%D8%AA%22",
    "tweet_volume": 10213
   },
   {
    "name": "الفريق الايراني",
    "url": "http://twitter.com/search?q=%22%D8%A7%D9%84%D9%81%D8%B1%D9%8A%D9%82+%D8%A7%D9%84%D8%A7%D9%8A%D8%B1%D8%A7%D9%86%D9%8A%22",
    "promoted_content": null,
    "query": "%22%D8%A7%D9%84%D9%81%D8%B1%D9%8A%D9%82+%D8%A7%D9%84%D8%A7%D9%8A%D8%B1%D8%A7%D9%86%D9%8A%22",
    "tweet_volume": null
   },
   {
    "name": "قوه الشخصيه",
    "url": "http://twitter.com/search?q=%22%D9%82%D9%88%D9%87+%D8%A7%D9%84%D8%B4%D8%AE%D8%B5%D9%8A%D9%87%22",
    "promoted_content": null,
    "query": "%22%D9%82%D9%88%D9%87+%D8%A7%D9%84%D8%B4%D8%AE%D8%B5%D9%8A%D9%87%22",
    "tweet_volume": null
   },
   {
    "name": "Baekhyun",
    "url": "http://twitter.com/search?q=Baekhyun",
    "promoted_content": null,
    "query": "Baekhyun",
    "tweet_volume": 118363
   },
   {
    "name": "مشعل",
    "url": "http://twitter.com/search?q=%D9%85%D8%B4%D8%B9%D9%84",
    "promoted_content": null,
    "query": "%D9%85%D8%B4%D8%B9%D9%84",
    "tweet_volume": null
   },
   {
    "name": "نعمه الامن",
    "url": "http://twitter.com/search?q=%22%D9%86%D8%B9%D9%85%D9%87+%D8%A7%D9%84%D8%A7%D9%85%D9%86%22",
    "promoted_content": null,
    "query": "%22%D9%86%D8%B9%D9%85%D9%87+%D8%A7%D9%84%D8%A7%D9%85%D9%86%22",
    "tweet_volume": null
   },
   {
    "name": "العصيمي",
    "url": "http://twitter.com/search?q=%D8%A7%D9%84%D8%B9%D8%B5%D9%8A%D9%85%D9%8A",
    "promoted_content": null,
    "query": "%D8%A7%D9%84%D8%B9%D8%B5%D9%8A%D9%85%D9%8A",
    "tweet_volume": null
   },
   {
    "name": "راكان",
    "url": "http://twitter.com/search?q=%D8%B1%D8%A7%D9%83%D8%A7%D9%86",
    "promoted_content": null,
    "query": "%D8%B1%D8%A7%D9%83%D8%A7%D9%86",
    "tweet_volume": null
   },
   {
    "name": "كبير اسيا",
    "url": "http://twitter.com/search?q=%22%D9%83%D8%A8%D9%8A%D8%B1+%D8%A7%D8%B3%D9%8A%D8%A7%22",
    "promoted_content": null,
    "query": "%22%D9%83%D8%A8%D9%8A%D8%B1+%D8%A7%D8%B3%D9%8A%D8%A7%22",
    "tweet_volume": null
   },
   {
    "name": "علي النبي",
    "url": "http://twitter.com/search?q=%22%D8%B9%D9%84%D9%8A+%D8%A7%D9%84%D9%86%D8%A8%D9%8A%22",
    "promoted_content": null,
    "query": "%22%D8%B9%D9%84%D9%8A+%D8%A7%D9%84%D9%86%D8%A8%D9%8A%22",
    "tweet_volume": 40608
   },
   {
    "name": "بويول",
    "url": "http://twitter.com/search?q=%D8%A8%D9%88%D9%8A%D9%88%D9%84",
    "promoted_content": null,
    "query": "%D8%A8%D9%88%D9%8A%D9%88%D9%84",
    "tweet_volume": null
   },
   {
    "name": "الرياض",
    "url": "http://twitter.com/search?q=%D8%A7%D9%84%D8%B1%D9%8A%D8%A7%D8%B6",
    "promoted_content": null,
    "query": "%D8%A7%D9%84%D8%B1%D9%8A%D8%A7%D8%B6",
    "tweet_volume": 182285
   },
   {
    "name": "اليونايتد",
    "url": "http://twitter.com/search?q=%D8%A7%D9%84%D9%8A%D9%88%D9%86%D8%A7%D9%8A%D8%AA%D8%AF",
    "promoted_content": null,
    "query": "%D8%A7%D9%84%D9%8A%D9%88%D9%86%D8%A7%D9%8A%D8%AA%D8%AF",
    "tweet_volume": null
   }
  ],
  "as_of": "2021-09-09T20:08:02Z",
  "created_at": "2021-08-21T18:01:59Z",
  "locations": [
   {
    "name": "Medina",
    "woeid": 1937801
   }
  ]
 }
]